genlib/__init__.py
genlib/ansiec.py
genlib/ican.py
genlib/slip.py
genlib/udp.py
pop_genlib-0.0.1.dist-info/METADATA
pop_genlib-0.0.1.dist-info/WHEEL
pop_genlib-0.0.1.dist-info/top_level.txt
pop_genlib-0.0.1.dist-info/RECORD
